memdocs/__init__.py
memdocs/cli.py
memdocs/cli_output.py
memdocs/embeddings.py
memdocs/empathy_adapter.py
memdocs/exceptions.py
memdocs/extract.py
memdocs/guard.py
memdocs/index.py
memdocs/mcp_server.py
memdocs/policy.py
memdocs/schemas.py
memdocs/search.py
memdocs/security.py
memdocs/summarize.py
memdocs/symbol_extractor.py
memdocs/cli_modules/__init__.py
memdocs/cli_modules/utils.py
memdocs/cli_modules/commands/__init__.py
memdocs/cli_modules/commands/cleanup_cmd.py
memdocs/cli_modules/commands/doctor_cmd.py
memdocs/cli_modules/commands/export_cmd.py
memdocs/cli_modules/commands/init_cmd.py
memdocs/cli_modules/commands/query_cmd.py
memdocs/cli_modules/commands/review_cmd.py
memdocs/cli_modules/commands/serve_cmd.py
memdocs/cli_modules/commands/setup_hooks_cmd.py
memdocs/cli_modules/commands/stats_cmd.py
memdocs/cli_modules/commands/update_config_cmd.py
memdocs-2.1.4.dist-info/licenses/LICENSE
memdocs-2.1.4.dist-info/METADATA
memdocs-2.1.4.dist-info/WHEEL
memdocs-2.1.4.dist-info/entry_points.txt
memdocs-2.1.4.dist-info/top_level.txt
memdocs-2.1.4.dist-info/RECORD
