Metadata-Version: 2.4
Name: memdocs
Version: 2.1.4
Summary: Persistent memory management for AI projects - Git-native documentation intelligence
Author-email: Patrick Roebuck <patrick.roebuck@smartaimemory.com>
License: Apache-2.0
Project-URL: Homepage, https://github.com/Smart-AI-Memory/memdocs
Project-URL: Documentation, https://docs.smartaimemory.com/memdocs
Project-URL: Repository, https://github.com/Smart-AI-Memory/memdocs
Project-URL: Issues, https://github.com/Smart-AI-Memory/memdocs/issues
Project-URL: Changelog, https://github.com/Smart-AI-Memory/memdocs/blob/main/CHANGELOG.md
Keywords: ai-memory,documentation,git-native,claude,empathy-framework,code-intelligence,developer-tools
Classifier: Development Status :: 5 - Production/Stable
Classifier: Intended Audience :: Developers
Classifier: License :: OSI Approved :: Apache Software License
Classifier: Programming Language :: Python :: 3
Classifier: Programming Language :: Python :: 3.10
Classifier: Programming Language :: Python :: 3.11
Classifier: Programming Language :: Python :: 3.12
Classifier: Topic :: Software Development :: Documentation
Classifier: Topic :: Software Development :: Libraries :: Python Modules
Requires-Python: >=3.10
License-File: LICENSE
Requires-Dist: click>=8.1.0
Requires-Dist: pydantic>=2.0.0
Requires-Dist: pyyaml>=6.0
Requires-Dist: anthropic>=0.34.0
Requires-Dist: gitpython>=3.1.40
Requires-Dist: tree-sitter>=0.21.0
Requires-Dist: pygments>=2.17.0
Requires-Dist: tiktoken>=0.7.0
Requires-Dist: python-dotenv>=1.0.0
Requires-Dist: rich>=13.0.0
Requires-Dist: tomli>=2.0.0; python_version < "3.11"
Provides-Extra: dev
Requires-Dist: pytest>=7.4.0; extra == "dev"
Requires-Dist: pytest-cov>=4.1.0; extra == "dev"
Requires-Dist: pytest-asyncio>=0.21.0; extra == "dev"
Requires-Dist: black>=24.0.0; extra == "dev"
Requires-Dist: ruff>=0.5.0; extra == "dev"
Requires-Dist: mypy>=1.10.0; extra == "dev"
Requires-Dist: types-pyyaml; extra == "dev"
Provides-Extra: api
Requires-Dist: fastapi>=0.112.0; extra == "api"
Requires-Dist: uvicorn[standard]>=0.30.0; extra == "api"
Requires-Dist: httpx>=0.27.0; extra == "api"
Provides-Extra: embeddings
Requires-Dist: openai>=1.40.0; extra == "embeddings"
Requires-Dist: pinecone-client>=5.0.0; extra == "embeddings"
Requires-Dist: numpy>=1.26.0; extra == "embeddings"
Requires-Dist: sentence-transformers>=2.0.0; extra == "embeddings"
Requires-Dist: faiss-cpu>=1.7.0; extra == "embeddings"
Provides-Extra: empathy
Requires-Dist: empathy>=1.0.0; extra == "empathy"
Provides-Extra: mcp
Requires-Dist: mcp>=1.0.0; extra == "mcp"
Provides-Extra: docs
Requires-Dist: mkdocs>=1.5.0; extra == "docs"
Requires-Dist: mkdocs-material>=9.0.0; extra == "docs"
Provides-Extra: all
Requires-Dist: memdocs[api,dev,docs,embeddings,empathy,mcp]; extra == "all"
Dynamic: license-file
